cubicweb_signedrequest/__init__.py
cubicweb_signedrequest/__pkginfo__.py
cubicweb_signedrequest/authplugin.py
cubicweb_signedrequest/entities.py
cubicweb_signedrequest/hooks.py
cubicweb_signedrequest/pconfig.py
cubicweb_signedrequest/schema.py
cubicweb_signedrequest/site_cubicweb.py
cubicweb_signedrequest/tools.py
cubicweb_signedrequest/views.py
cubicweb_signedrequest/doc/sreq_example.py
cubicweb_signedrequest/i18n/en.po
cubicweb_signedrequest/i18n/es.po
cubicweb_signedrequest/i18n/fr.po
cubicweb_signedrequest/migration/0.2.0_Any.py
cubicweb_signedrequest/migration/0.3.0_Any.py
cubicweb_signedrequest/migration/2.1.0_Any.py
cubicweb_signedrequest-3.3.1.dist-info/METADATA
cubicweb_signedrequest-3.3.1.dist-info/WHEEL
cubicweb_signedrequest-3.3.1.dist-info/entry_points.txt
cubicweb_signedrequest-3.3.1.dist-info/top_level.txt
cubicweb_signedrequest-3.3.1.dist-info/RECORD
