Metadata-Version: 2.4
Name: cubicweb-signedrequest
Version: 3.3.1
Summary: REST API for CubicWeb
Author-email: Logilab <contact@logilab.fr>
License: GNU Lesser General Public License v2 or later (LGPLv2+)
Project-URL: Issues, https://forge.extranet.logilab.fr/cubicweb/cubes/signedrequest/-/issues
Project-URL: Repository, https://forge.extranet.logilab.fr/cubicweb/cubes/signedrequest
Classifier: Environment :: Web Environment
Classifier: Framework :: CubicWeb
Classifier: Programming Language :: Python
Classifier: Programming Language :: Python :: 3
Classifier: Programming Language :: Python :: 3 :: Only
Classifier: Programming Language :: JavaScript
Requires-Python: >=3.11
Requires-Dist: cubicweb<6.0.0,>=4.5.2
